tests/__init__.py
tests/__main__.py
tests/admin.py
tests/test_flash.py
tests/test_handlers.py
tests/utils/__init__.py
tests/utils/test_template.py
tornadmin/__init__.py
tornadmin/decorators.py
tornadmin/flash.py
tornadmin/handlers.py
tornadmin/routes.py
tornadmin/sites.py
tornadmin/uimodules.py
tornadmin/backends/__init__.py
tornadmin/backends/base.py
tornadmin/backends/forms.py
tornadmin/backends/widgets.py
tornadmin/backends/tortoise/__init__.py
tornadmin/backends/tortoise/actions.py
tornadmin/backends/tortoise/admin.py
tornadmin/backends/tortoise/forms.py
tornadmin/backends/tortoise/paginator.py
tornadmin/static/tornadmin/main.js
tornadmin/static/tornadmin/style.css
tornadmin/static/tornadmin/img/icon.png
tornadmin/static/tornadmin/img/nav-logo.png
tornadmin/static/tornadmin/img/splash.png
tornadmin/static/tornadmin/vendor/jquery-3.3.1.min.js
tornadmin/static/tornadmin/vendor/bootstrap/css/bootstrap.min.css
tornadmin/static/tornadmin/vendor/bootstrap/css/bootstrap.min.css.map
tornadmin/static/tornadmin/vendor/bootstrap/icons/bootstrap-icons.css
tornadmin/static/tornadmin/vendor/bootstrap/icons/fonts/bootstrap-icons.woff
tornadmin/static/tornadmin/vendor/bootstrap/icons/fonts/bootstrap-icons.woff2
tornadmin/static/tornadmin/vendor/bootstrap/js/bootstrap.bundle.min.js
tornadmin/static/tornadmin/vendor/bootstrap/js/bootstrap.bundle.min.js.map
tornadmin/templates/base.html
tornadmin/templates/base_site.html
tornadmin/templates/create.html
tornadmin/templates/index.html
tornadmin/templates/list.html
tornadmin/templates/login.html
tornadmin/templates/modules/flash.html
tornadmin/templates/modules/header.html
tornadmin/templates/modules/pagination.html
tornadmin/templates/modules/side-nav.html
tornadmin/utils/__init__.py
tornadmin/utils/escape.py
tornadmin/utils/paginator.py
tornadmin/utils/template.py
tornadmin/utils/text.py
tornadmin-0.9.1.dist-info/LICENSE.txt
tornadmin-0.9.1.dist-info/METADATA
tornadmin-0.9.1.dist-info/WHEEL
tornadmin-0.9.1.dist-info/top_level.txt
tornadmin-0.9.1.dist-info/RECORD
